{"inkVersion":21,"root":[["\n","ev",{"VAR?":"choiceMake"},"str","^","/str","==","/ev",[{"->":".^.b","c":true},{"b":["^ ",{"->":"main"},{"->":"0.10"},null]}],[{"->":".^.b"},{"b":[{"->":"alreadyChose"},{"->":"0.10"},null]}],"nop","\n",{"->":"main"},["done",{"#f":5,"#n":"g-0"}],null],"done",{"main":[["^hallo perkenalkan nama aku Toba ","#","^speaker:<color=#228B22>ToadKing</color> ","/#","#","^potrait:ToadKing_Talking ","/#","#","^layout:right","/#","\n","^siapakah nama kamu <color=#FFC0CB>ganteng</color>","\n",["ev",{"^->":"main.0.13.$r1"},{"temp=":"$r"},"str",{"->":".^.s"},[{"#n":"$r1"}],"/str","/ev",{"*":".^.^.c-0","flg":18},{"s":["^Perkenalkan Nama aku Adi ","#","^speaker:Adi ","/#","#","^potrait:Player_Calm","/#","#","^layout:left","/#",{"->":"$r","var":true},null]}],["ev",{"^->":"main.0.14.$r1"},{"temp=":"$r"},"str",{"->":".^.s"},[{"#n":"$r1"}],"/str","/ev",{"*":".^.^.c-1","flg":18},{"s":["^Tidak Perlu Tau Namaku Siapa ! ","#","^speaker:Adi ","/#","#","^potrait:Player_Calm","/#","#","^layout:left","/#",{"->":"$r","var":true},null]}],{"c-0":["ev",{"^->":"main.0.c-0.$r2"},"/ev",{"temp=":"$r"},{"->":".^.^.13.s"},[{"#n":"$r2"}],"\n","^Salam Kenal ya agus, senang bertemu dengan kamu. ","#","^speaker:<color=#228B22>ToadKing</color> ","/#","#","^potrait:ToadKing_Amazed ","/#","#","^layout:right","/#","\n",{"->":".^.^.g-0"},{"#f":5}],"c-1":["ev",{"^->":"main.0.c-1.$r2"},"/ev",{"temp=":"$r"},{"->":".^.^.14.s"},[{"#n":"$r2"}],"\n","^okay jika begitu, tidak perlu marah seperti itu kawan.  ","#","^speaker:<color=#228B22>ToadKing</color> ","/#","#","^potrait:ToadKing_Angry  ","/#","#","^layout:right","/#","\n",{"->":".^.^.g-0"},{"#f":5}],"g-0":["^oiyaa aku ada rencana nih untuk meninggalkan tempat ini","#","^speaker:<color=#228B22>ToadKing</color> ","/#","#","^potrait:ToadKing_Talking ","/#","#","^layout:right","/#","\n","^yuk berkelana bersama dengan saya mencari ciwi ciwi cantik dan sexy","\n","^(ada yang aneh dengan orang ini seperti pernah melihatnya dalam suatu buku ??) ","#","^speaker:Adi ","/#","#","^potrait:Player_Calm","/#","#","/#","#","^layout:left","/#","\n","^(hmmm apakah sebaaiknya aku bantu saja dia ya ??)","#","^speaker:Adi ","/#","#","^potrait:Player_Calm","/#","#","^layout:left","/#","\n","ev","str","^Hayukkk","/str","/ev",{"*":".^.c-2","flg":4},"ev","str","^Tidak Mau","/str","/ev",{"*":".^.c-3","flg":4},{"c-2":["^ ","\n","ev","str","^hayukk","/str","/ev",{"->":"chosen"},"^yukk kita mencari cewe cewe sexy dan cantikk cantikk","\n",{"#f":5}],"c-3":["\n","^maaf aku tidak ikut dahulu lagi malas sekali","\n","ev","str","^Tidak mau","/str","/ev",{"->":"chosen"},{"#f":5}],"#f":5}]}],{"#f":1}],"chosen":[{"temp=":"pilihan"},"ev",{"VAR?":"pilihan"},"/ev",{"VAR=":"choiceMake","re":true},["ev",{"VAR?":"pilihan"},"str","^hayukk","/str","==","/ev",{"->":".^.b","c":true},{"b":["\n","^lets gooooooo !!!!","#","^speaker:<color=#228B22>ToadKing</color> ","/#","#","^potrait:ToadKing_Confused ","/#","#","^layout:right","/#","\n",{"->":"chosen.7"},null]}],["ev",{"VAR?":"pilihan"},"str","^Tidak mau","/str","==","/ev",{"->":".^.b","c":true},{"b":["\n","^cari aku jika kamu berubah pikiran ya ","#","^speaker:<color=#228B22>ToadKing</color> ","/#","#","^potrait:ToadKing_Confused ","/#","#","^layout:right","/#","\n",{"->":"chosen.7"},null]}],"nop","\n","end",{"#f":1}],"alreadyChose":[["ev",{"VAR?":"choiceMake"},"str","^hayukk","/str","==","/ev",{"->":".^.b","c":true},{"b":["\n","^tunggu apa lagi ayuk jalan","#","^speaker:<color=#228B22>ToadKing</color> ","/#","#","^potrait:ToadKing_Talking ","/#","#","^layout:right","/#","\n",{"->":".^.^.^.2"},null]}],["ev",{"VAR?":"choiceMake"},"str","^Tidak mau","/str","==","/ev",{"->":".^.b","c":true},{"b":["\n","^apakah kamu berubah pikiran ganteng ?? ","#","^speaker:<color=#228B22>ToadKing</color> ","/#","#","^potrait:ToadKing_Talking ","/#","#","^layout:right","/#","\n",{"->":".^.^.^.2"},null]}],"nop","\n","end",{"#f":1}],"global decl":["ev","str","^","/str",{"VAR=":"choiceMake"},"/ev","end",null],"#f":1}],"listDefs":{}}